---
layout:     post
title:      枚举
subtitle:   枚举不得不说的地方
date:       2020-05-09
author:     tryingpfq
header-img: img/post-bg-enum.jpg
catalog: true
tags:

    - 枚举
---

### 概述

首先对于一个枚举，每一个枚举对象都是一个单例。编译后，会为每一个单例创建一个class文件（但是发现并不是这样的。**问题来了，为什么有的编译后只有一个文件AEnum.class，有时候可能存在多个：BEnum$1.class、BEnum$2.class...）。**

### 不得不说的方法

了解枚举几个方法`java.lang.Enum` 

* 1: ordinal() 这个返回的是枚举中每个对象的唯一顺序，这个貌似是和源代码属性一致(不太确定，是否和编译有关，所以这个地方容易出现问题，就是加入不小心，改变了顺序，那么就会出问题)，默认是从0开始。

* 2: name()  这个返回的是枚举中每个对象的字段名

* 3: values() 返回该枚举类中对象的数据，这个方法是编译生成的，在父类中也是没有的哦。看后面字节码吧

* 4: valueOf(..) 这个方法，可以仔了解下哦

```java
//看这个方法，很明显，要根据这个枚举类类型和name,才能唯一获取这个枚举实例
public static <T extends Enum<T>> T valueOf(Class<T> enumType,
                                                String name) {
     	//可见，针对每一个枚举类类型都有一个缓存
        T result = enumType.enumConstantDirectory().get(name);
        if (result != null)
            return result;
        if (name == null)
            throw new NullPointerException("Name is null");
        throw new IllegalArgumentException(
            "No enum constant " + enumType.getCanonicalName() + "." + name);
    }
```

有必要看看上面这个地方：`enumType.enumConstantDirectory().get(name)`

这个`java.lang.Class#enumConstantDirectory`看名字就知道，这个是专门给枚举做缓存注册用的。

看下上面这个方法，很明显看出这个是一个懒加载的过程。

```java
 Map<String, T> enumConstantDirectory() {
        if (enumConstantDirectory == null) {
            T[] universe = getEnumConstantsShared();
            if (universe == null)
                throw new IllegalArgumentException(
                    getName() + " is not an enum type");
            Map<String, T> m = new HashMap<>(2 * universe.length);
            //这里是一个懒加载的过程。但又要继续了解这个universe是如何来的
            for (T constant : universe)
                m.put(((Enum<?>)constant).name(), constant);
            enumConstantDirectory = m;
        }
        return enumConstantDirectory;
    }
```

继续看

```java
T[] getEnumConstantsShared() {
        if (enumConstants == null) {
            //很明显这里判断是否为枚举
            if (!isEnum()) return null;
            try {
                //调用枚举的时候，会返回这个枚举的所有对象数组，但是不是死活找不到这个values方法，
                //下面把字节码贴出来就知道了
                final Method values = getMethod("values");
                java.security.AccessController.doPrivileged(
                    new java.security.PrivilegedAction<Void>() {
                        public Void run() {
                                values.setAccessible(true);
                                return null;
                            }
                        });
                @SuppressWarnings("unchecked")
                T[] temporaryConstants = (T[])values.invoke(null);
                enumConstants = temporaryConstants;
        }
        return enumConstants;
    }
```



### 一个枚举类的字节码文件

```java
public final enum com/tryingpfq/enums/MyEnum extends java/lang/Enum  {
	//很明显父类是Enum
  // compiled from: MyEnum.java

  // access flags 0x4019
  public final static enum Lcom/tryingpfq/enums/MyEnum; One

  // access flags 0x4019
  public final static enum Lcom/tryingpfq/enums/MyEnum; Two

  // access flags 0x2
  private I id

  // access flags 0x101A
  private final static synthetic [Lcom/tryingpfq/enums/MyEnum; $VALUES

  // access flags 0x9
  public static values()[Lcom/tryingpfq/enums/MyEnum;
   L0
    LINENUMBER 7 L0
    GETSTATIC com/tryingpfq/enums/MyEnum.$VALUES : [Lcom/tryingpfq/enums/MyEnum;
    INVOKEVIRTUAL [Lcom/tryingpfq/enums/MyEnum;.clone ()Ljava/lang/Object;
    CHECKCAST [Lcom/tryingpfq/enums/MyEnum;
    ARETURN
    MAXSTACK = 1
    MAXLOCALS = 0

  // access flags 0x9
  public static valueOf(Ljava/lang/String;)Lcom/tryingpfq/enums/MyEnum;
   L0
    LINENUMBER 7 L0
    LDC Lcom/tryingpfq/enums/MyEnum;.class
    ALOAD 0
    //调用父类的valueOf()方法
    INVOKESTATIC java/lang/Enum.valueOf 	(Ljava/lang/Class;Ljava/lang/String;)Ljava/lang/Enum;
    CHECKCAST com/tryingpfq/enums/MyEnum
    ARETURN
   L1
    LOCALVARIABLE name Ljava/lang/String; L0 L1 0
    MAXSTACK = 2
    MAXLOCALS = 1

  // access flags 0x2
  // signature (I)V
  // declaration: void <init>(int)
  private <init>(Ljava/lang/String;II)V
   L0
    LINENUMBER 16 L0
    ALOAD 0
    ALOAD 1
    ILOAD 2
    INVOKESPECIAL java/lang/Enum.<init> (Ljava/lang/String;I)V
   L1
    LINENUMBER 17 L1
    ALOAD 0
    ILOAD 3
    PUTFIELD com/tryingpfq/enums/MyEnum.id : I
   L2
    LINENUMBER 18 L2
    RETURN
   L3
    LOCALVARIABLE this Lcom/tryingpfq/enums/MyEnum; L0 L3 0
    LOCALVARIABLE id I L0 L3 3
    MAXSTACK = 3
    MAXLOCALS = 4

  // access flags 0x8
  static <clinit>()V
   L0
    LINENUMBER 9 L0
    NEW com/tryingpfq/enums/MyEnum
    DUP
    LDC "One"
    ICONST_0
    ICONST_1
    INVOKESPECIAL com/tryingpfq/enums/MyEnum.<init> (Ljava/lang/String;II)V
    PUTSTATIC com/tryingpfq/enums/MyEnum.One : Lcom/tryingpfq/enums/MyEnum;
   L1
    LINENUMBER 11 L1
    NEW com/tryingpfq/enums/MyEnum
    DUP
    LDC "Two"
    ICONST_1
    ICONST_2
    INVOKESPECIAL com/tryingpfq/enums/MyEnum.<init> (Ljava/lang/String;II)V
    PUTSTATIC com/tryingpfq/enums/MyEnum.Two : Lcom/tryingpfq/enums/MyEnum;
   L2
    LINENUMBER 7 L2
    ICONST_2
    ANEWARRAY com/tryingpfq/enums/MyEnum
    DUP
    ICONST_0
    GETSTATIC com/tryingpfq/enums/MyEnum.One : Lcom/tryingpfq/enums/MyEnum;
    AASTORE
    DUP
    ICONST_1
    GETSTATIC com/tryingpfq/enums/MyEnum.Two : Lcom/tryingpfq/enums/MyEnum;
    AASTORE
    PUTSTATIC com/tryingpfq/enums/MyEnum.$VALUES : [Lcom/tryingpfq/enums/MyEnum;
    RETURN
    MAXSTACK = 5
    MAXLOCALS = 0
}

```



### 序列化和反序列化

在序列化的时候Java仅仅是将枚举对象的name属性输出到结果中，反序列化的时候则是通过java.lang.Enum的valueOf方法来根据名字查找枚举对象。同时，编译器是不允许任何对这种序列化机制的定制的，因此禁用了`writeObject、readObject、readObjectNoData、writeReplace`和`readResolve`等方法。

fastjson中，枚举序列化看下这个方法：

`com.alibaba.fastjson.serializer.SerializeWriter#writeEnum`很明显里面调用的是name方法，当要序列化为整数的时候，会调用ordinal这个方法，**但是我目前不知道这个怎么整**。

反序列化：`EnumDeserializer`

#### 存在的问题
上面是说序列化和反序列化问题，其实枚举持久化也会有问题。

使用枚举类型进行映射有一个弊端就是，将来有一天修改了枚举类型的定义**会造成数据库中的数据无法被加载**，所以如果对改动的枚举定义(如顺序调整了-- ORDINAL; 或名称改了; 或增减了选项) 时一定要同步 update 数据库中的记录，这对于产品数据库也是个麻烦事。**这一点上还是需要谨慎的思考是否真要用 Java 的枚举值来映射**。[博文](https://yanbin.blog/hibernate-map-enum-type-field/)

* 既然存在问题，那么该如何去解决呢？
1：自定义枚举的序列化和反序列化工具
2：实现假枚举(`FakeEnum`),这个太复杂了，有待于研究。



### 枚举单例的实现

枚举类中，每一个对象都是一个唯一的单例。

```java
public enum  SingletonEnum {
    //这其实就是一个单例了
    INSTANCE;
    private String name;
    public String getName(){
        return name;
    }
    public void setName(String name){
        this.name = name;
    }
}

```



枚举序列化是如何保证不破坏单例的呢？简单理解就是，枚举反序列化的时候，并不是根据反射，而是根据这个枚举类的valueOf()方法，本身在这个**枚举类对象**中就是一个缓存。

枚举序列化是由jvm保证的，每一个枚举类型和定义的枚举变量在JVM中都是唯一的，在枚举类型的序列化和反序列化上，Java做了特殊的规定：在序列化时Java仅仅是将枚举对象的name属性输出到结果中，反序列化的时候则是通过java.lang.Enum的valueOf方法来根据名字查找枚举对象。同时，编译器是不允许任何对这种序列化机制的定制的并禁用了writeObject、readObject、readObjectNoData、writeReplace和readResolve等方法，从而保证了枚举实例的唯一性


### 假枚举的实现



[参考博文1](https://blog.csdn.net/hupoling/article/details/74990456)    [参考博文2](https://blog.csdn.net/javazejian/article/details/71333103?utm_medium=distribute.pc_relevant.none-task-blog-BlogCommendFromBaidu-12&depth_1-utm_source=distribute.pc_relevant.none-task-blog-BlogCommendFromBaidu-12)